agentcheck/__init__.py
agentcheck/asserts.py
agentcheck/cli.py
agentcheck/diff.py
agentcheck/replay.py
agentcheck/trace.py
agentcheck/utils.py
agentcheck-0.1.0.dist-info/licenses/LICENSE
agentcheck-0.1.0.dist-info/METADATA
agentcheck-0.1.0.dist-info/WHEEL
agentcheck-0.1.0.dist-info/entry_points.txt
agentcheck-0.1.0.dist-info/top_level.txt
agentcheck-0.1.0.dist-info/RECORD
