Metadata-Version: 2.4
Name: agentcheck
Version: 0.1.0
Summary: Trace ⋅ Replay ⋅ Test your AI agents like real software
Author: AgentCheck Contributors
License-Expression: MIT
Project-URL: Homepage, https://github.com/agentcheck/agentcheck
Project-URL: Repository, https://github.com/agentcheck/agentcheck
Project-URL: Issues, https://github.com/agentcheck/agentcheck/issues
Classifier: Development Status :: 4 - Beta
Classifier: Intended Audience :: Developers
Classifier: Programming Language :: Python :: 3
Classifier: Programming Language :: Python :: 3.9
Classifier: Programming Language :: Python :: 3.10
Classifier: Programming Language :: Python :: 3.11
Classifier: Programming Language :: Python :: 3.12
Requires-Python: >=3.9
License-File: LICENSE
Requires-Dist: openai>=1.0.0
Requires-Dist: jsonschema>=4.0.0
Requires-Dist: rich>=13.0.0
Requires-Dist: jsonpath-ng>=1.5.0
Provides-Extra: dev
Requires-Dist: pytest>=7.0.0; extra == "dev"
Requires-Dist: ruff>=0.1.0; extra == "dev"
Requires-Dist: mypy>=1.0.0; extra == "dev"
Dynamic: license-file
